{
    "result": "1",
    "data": [
        {
            "advImage": "http://i1.1688wan.com/allimgs/img_inews/201607/_1469859715190.jpg",
            "advType": "1",
            "advId": "333333"		
        },
        {
            "advImage": "http://ww4.sinaimg.cn/orj480/005SD59Cgw1f7mgc5numgj30jg0fagnn.jpg",
            "advType": "1",
            "advId": "333333"		
        },
        {
            "advImage": "http://s3.actoys.net/pcupload/2016/0330/20160330115115232.jpg",
            "advType": "1",
            "advId": "333333"		
        }
    ]
}